ga4_mcp/__init__.py
ga4_mcp/__main__.py
ga4_mcp/coordinator.py
ga4_mcp/server.py
ga4_mcp/tools/metadata.py
ga4_mcp/tools/reporting.py
google_analytics_mcp-2.0.0.dist-info/METADATA
google_analytics_mcp-2.0.0.dist-info/WHEEL
google_analytics_mcp-2.0.0.dist-info/entry_points.txt
google_analytics_mcp-2.0.0.dist-info/top_level.txt
google_analytics_mcp-2.0.0.dist-info/RECORD
