Metadata-Version: 2.4
Name: google-analytics-mcp
Version: 2.0.0
Summary: Google Analytics 4 MCP Server with Smart Optimizations - Access GA4 data in Claude, Cursor and other MCP clients. Prevents context window crashes with intelligent data volume management.
Author-email: Surendran B <reachsuren@gmail.com>
License: MIT
Project-URL: Homepage, https://github.com/surendranb/google-analytics-mcp
Project-URL: Repository, https://github.com/surendranb/google-analytics-mcp
Project-URL: Issues, https://github.com/surendranb/google-analytics-mcp/issues
Keywords: google-analytics,mcp,ai-assistant,analytics,ga4,claude,cursor,windsurf
Classifier: Development Status :: 5 - Production/Stable
Classifier: Intended Audience :: Developers
Classifier: License :: OSI Approved :: MIT License
Classifier: Programming Language :: Python :: 3
Classifier: Programming Language :: Python :: 3.10
Classifier: Programming Language :: Python :: 3.11
Classifier: Programming Language :: Python :: 3.12
Classifier: Programming Language :: Python :: 3.13
Requires-Python: >=3.10
Requires-Dist: mcp>=1.2.0
Requires-Dist: google-analytics-data==0.19.0
Requires-Dist: google-auth==2.40.0
